<manifest alg="2" build="2015.0.0.309" opt="false" iceEnabled="true" iceMarkupVersion="2" exportTarget="other" domain="caravana.com" resolutions="1x" timestamp="1474232225213">
  <folder name="css">
    <file name="site_global.css" crc="4052507572"/>
    <file name="master_a-mestre.css" crc="97807657" ref="participante:evento:index:transporte:caravana"/>
    <file name="participante.css" crc="428278761" ref="participante"/>
    <file name="evento.css" crc="3995286201" ref="evento"/>
    <file name="index.css" crc="291440183" ref="index"/>
    <file name="transporte.css" crc="4253837294" ref="transporte"/>
    <file name="caravana.css" crc="423882076" ref="caravana"/>
  </folder>
  <folder name="scripts">
    <file name="jquery-1.8.3.min.js" crc="4255413929" ref="index:caravana:evento:participante:transporte"/>
    <file name="museutils.js" crc="183364071" ref="index:caravana:evento:participante:transporte"/>
    <file name="jquery.musepolyfill.bgsize.js" crc="4004268962" ref="index"/>
    <file name="pie.js" crc="3827607177" ref="index"/>
    <file name="jquery.watch.js" crc="71412426" ref="index:caravana:evento:participante:transporte"/>
    <file name="webpro.js" crc="3803554875" ref="caravana:evento:participante:transporte"/>
    <file name="form_check.php" crc="277267350" ref="caravana:evento:participante:transporte"/>
    <file name="form_throttle.php" crc="3908387251" ref="caravana:evento:participante:transporte"/>
    <file name="form_process.php" crc="24249335" ref="caravana:evento:participante:transporte"/>
    <file name="form-u377.php" crc="4198777319" ref="caravana"/>
    <file name="form-u336.php" crc="498071651" ref="evento"/>
    <file name="form-u295.php" crc="4259514433" ref="participante"/>
    <file name="form-u252.php" crc="423897497" ref="transporte"/>
  </folder>
  <folder name="images">
    <file name="bg.jpg" crc="214880899" ref="index"/>
    <file name="firefox6-1.png" crc="472318868" seo="true" ref="index:caravana:evento:participante:transporte"/>
    <file name="blank.gif" crc="4208392903" ref="index:caravana:evento:participante:transporte"/>
    <file name="u121_states.png" crc="3776314240" ref="index:caravana:evento:participante:transporte"/>
    <file name="u121_states-r.png" crc="4041017046" ref="index:caravana:evento:participante:transporte"/>
    <file name="u121_states-a.png" crc="4041017046" ref="index:caravana:evento:participante:transporte"/>
    <file name="u122_states.png" crc="70710370" ref="index:caravana:evento:participante:transporte"/>
    <file name="u122_states-r.png" crc="3981940919" ref="index:caravana:evento:participante:transporte"/>
    <file name="u122_states-a.png" crc="3981940919" ref="index:caravana:evento:participante:transporte"/>
    <file name="u123_states.png" crc="4206664546" ref="index:caravana:evento:participante:transporte"/>
    <file name="u123_states-r.png" crc="3920278451" ref="index:caravana:evento:participante:transporte"/>
    <file name="u123_states-a.png" crc="3920278451" ref="index:caravana:evento:participante:transporte"/>
    <file name="u124_states.png" crc="391709490" ref="index:caravana:evento:participante:transporte"/>
    <file name="u124_states-r.png" crc="442330433" ref="index:caravana:evento:participante:transporte"/>
    <file name="u124_states-a.png" crc="442330433" ref="index:caravana:evento:participante:transporte"/>
    <file name="u125_states.png" crc="212372344" ref="index:caravana:evento:participante:transporte"/>
    <file name="u125_states-r.png" crc="151486249" ref="index:caravana:evento:participante:transporte"/>
    <file name="u125_states-a.png" crc="151486249" ref="index:caravana:evento:participante:transporte"/>
    <file name="caravana do silvio santos.png" crc="474675676" seo="true" ref="index:caravana:evento:participante:transporte"/>
    <file name="ico04b.png" crc="4190197735" seo="true" ref="index:caravana:evento:participante:transporte"/>
    <file name="ico01b-crop-u190.png" crc="3957668583" ref="index:caravana:evento:participante:transporte"/>
    <file name="ico02b-crop-u195.png" crc="3927403112" ref="index:caravana:evento:participante:transporte"/>
    <file name="ico05b.png" crc="4283193023" seo="true" ref="index:caravana:evento:participante:transporte"/>
    <file name="house-308936_960_720.png" crc="302983039" seo="true" ref="index:caravana:evento:participante:transporte"/>
    <file name="top.png" crc="3865332595" seo="true" ref="index"/>
    <file name="rf16-splash.png" crc="3901910727" seo="true" ref="index"/>
    <file name="u418-4.png" crc="4261058123" ref="caravana"/>
    <file name="u408-17.png" crc="425091447" ref="caravana"/>
    <file name="u408-17-r.png" crc="481309586" ref="caravana"/>
    <file name="u408-17-m.png" crc="26342337" ref="caravana"/>
    <file name="u408-17-fs.png" crc="334091950" ref="caravana"/>
    <file name="u419-4.png" crc="4073216556" ref="evento"/>
    <file name="u367-17.png" crc="425091447" ref="evento"/>
    <file name="u367-17-r.png" crc="481309586" ref="evento"/>
    <file name="u367-17-m.png" crc="26342337" ref="evento"/>
    <file name="u367-17-fs.png" crc="334091950" ref="evento"/>
    <file name="u420-4.png" crc="3887838771" ref="participante"/>
    <file name="u326-17.png" crc="425091447" ref="participante"/>
    <file name="u326-17-r.png" crc="481309586" ref="participante"/>
    <file name="u326-17-m.png" crc="26342337" ref="participante"/>
    <file name="u326-17-fs.png" crc="334091950" ref="participante"/>
    <file name="u421-4.png" crc="4275023502" ref="transporte"/>
    <file name="u283-17.png" crc="425091447" ref="transporte"/>
    <file name="u283-17-r.png" crc="481309586" ref="transporte"/>
    <file name="u283-17-m.png" crc="26342337" ref="transporte"/>
    <file name="u283-17-fs.png" crc="334091950" ref="transporte"/>
  </folder>
  <file name="index.html" crc="3911905613" seo="true" mt="1474230545312" redirect="true"/>
  <file name="caravana.html" crc="4158896532" seo="true" mt="1474232122028" redirect="true"/>
  <file name="evento.html" crc="12111009" seo="true" mt="1474232110747" redirect="true"/>
  <file name="participante.html" crc="3855352691" seo="true" mt="1474232102015" redirect="true"/>
  <file name="transporte.html" crc="341376818" seo="true" mt="1474232077794" redirect="true"/>
</manifest>